zipcreator/__init__.py
zipcreator/list_zip.py
zipcreator-1.0.1.dist-info/LICENSE.txt
zipcreator-1.0.1.dist-info/METADATA
zipcreator-1.0.1.dist-info/WHEEL
zipcreator-1.0.1.dist-info/top_level.txt
zipcreator-1.0.1.dist-info/RECORD
