Metadata-Version: 2.1
Name: zipcreator
Version: 1.0.1
Summary: A quick tool for creating a zipfile from a list of files and/or directories.
Home-page: https://github.com/mpalazzolo/zipcreator
Author: Matt Palazzolo
Author-email: mattpalazzolo@gmail.com
License: LICENSE.txt
Platform: UNKNOWN
